{
  "hash": "d2a9b755",
  "configHash": "113d45ac",
  "lockfileHash": "24289b47",
  "browserHash": "dbe9f629",
  "optimized": {
    "react": {
      "src": "../../node_modules/react/index.js",
      "file": "react.js",
      "fileHash": "90d0fe03",
      "needsInterop": true
    },
    "react-dom": {
      "src": "../../node_modules/react-dom/index.js",
      "file": "react-dom.js",
      "fileHash": "4da12183",
      "needsInterop": true
    },
    "react/jsx-dev-runtime": {
      "src": "../../node_modules/react/jsx-dev-runtime.js",
      "file": "react_jsx-dev-runtime.js",
      "fileHash": "34ec7484",
      "needsInterop": true
    },
    "react/jsx-runtime": {
      "src": "../../node_modules/react/jsx-runtime.js",
      "file": "react_jsx-runtime.js",
      "fileHash": "3b5b7a1f",
      "needsInterop": true
    },
    "@radix-ui/react-slot": {
      "src": "../../node_modules/@radix-ui/react-slot/dist/index.mjs",
      "file": "@radix-ui_react-slot.js",
      "fileHash": "45fd729c",
      "needsInterop": false
    },
    "class-variance-authority": {
      "src": "../../node_modules/class-variance-authority/dist/index.mjs",
      "file": "class-variance-authority.js",
      "fileHash": "7d81f0f3",
      "needsInterop": false
    },
    "clsx": {
      "src": "../../node_modules/clsx/dist/clsx.mjs",
      "file": "clsx.js",
      "fileHash": "2d207277",
      "needsInterop": false
    },
    "framer-motion": {
      "src": "../../node_modules/framer-motion/dist/es/index.mjs",
      "file": "framer-motion.js",
      "fileHash": "d509b115",
      "needsInterop": false
    },
    "lucide-react": {
      "src": "../../node_modules/lucide-react/dist/esm/lucide-react.js",
      "file": "lucide-react.js",
      "fileHash": "df58f1f9",
      "needsInterop": false
    },
    "react-dom/client": {
      "src": "../../node_modules/react-dom/client.js",
      "file": "react-dom_client.js",
      "fileHash": "4f6b64e8",
      "needsInterop": true
    },
    "react-router-dom": {
      "src": "../../node_modules/react-router-dom/dist/index.mjs",
      "file": "react-router-dom.js",
      "fileHash": "c7ee530c",
      "needsInterop": false
    },
    "tailwind-merge": {
      "src": "../../node_modules/tailwind-merge/dist/bundle-mjs.mjs",
      "file": "tailwind-merge.js",
      "fileHash": "55746482",
      "needsInterop": false
    }
  },
  "chunks": {
    "chunk-XHU36PYF": {
      "file": "chunk-XHU36PYF.js"
    },
    "chunk-KDVGFZWC": {
      "file": "chunk-KDVGFZWC.js"
    },
    "chunk-IHRST5LR": {
      "file": "chunk-IHRST5LR.js"
    },
    "chunk-32E4H3EV": {
      "file": "chunk-32E4H3EV.js"
    },
    "chunk-G3PMV62Z": {
      "file": "chunk-G3PMV62Z.js"
    }
  }
}